pythainance/__init__.py
pythainance/utils.py
pythainance/dataset/debt.xlsx
pythainance/dataset/reference.txt
pythainance/dataset/scraped_content.txt
pythainance/dataset/backup_dataset/debt.xlsx
pythainance/dataset/backup_dataset/interest_rate.xlsx
pythainance/dataset/backup_dataset/macro.xlsx
pythainance/debt/__init__.py
pythainance/debt/analysis.py
pythainance/debt/loader.py
pythainance/debt/visualization.py
pythainance/search/__init__.py
pythainance/search/scraper.py
pythainance-0.0.7.dist-info/LICENSE
pythainance-0.0.7.dist-info/METADATA
pythainance-0.0.7.dist-info/WHEEL
pythainance-0.0.7.dist-info/top_level.txt
pythainance-0.0.7.dist-info/RECORD
