Metadata-Version: 2.2
Name: pythainance
Version: 0.0.7
Summary: AI financial analysis library for Thai financial data
Home-page: https://github.com/PyThainance/PyThainance.git
Author: Warit Mahitti
Author-email: mrwaritmahitti@gmail.com
Classifier: Programming Language :: Python :: 3
Classifier: License :: OSI Approved :: MIT License
Classifier: Operating System :: OS Independent
Requires-Python: >=3.7
License-File: LICENSE
Requires-Dist: pandas
Requires-Dist: matplotlib
Requires-Dist: seaborn
Requires-Dist: openpyxl
Requires-Dist: playwright
Requires-Dist: beautifulsoup4
Dynamic: author
Dynamic: author-email
Dynamic: classifier
Dynamic: description
Dynamic: description-content-type
Dynamic: home-page
Dynamic: requires-dist
Dynamic: requires-python
Dynamic: summary
